{
  "table": [
    {
      "idStanding": "9353074",
      "intRank": "1",
      "idTeam": "133714",
      "strTeam": "Paris SG",
      "strBadge": "https://r2.thesportsdb.com/images/media/team/badge/rwqrrq1473504808.png/tiny",
      "idLeague": "4334",
      "strLeague": "French Ligue 1",
      "strSeason": "2025-2026",
      "strForm": "WWLWW",
      "strDescription": "Champions League",
      "intPlayed": "27",
      "intWin": "20",
      "intLoss": "4",
      "intDraw": "3",
      "intGoalsFor": "61",
      "intGoalsAgainst": "23",
      "intGoalDifference": "38",
      "intPoints": "63",
      "dateUpdated": "2026-04-15 23:02:30"
    },
    {
      "idStanding": "9353075",
      "intRank": "2",
      "idTeam": "133822",
      "strTeam": "Lens",
      "strBadge": "https://r2.thesportsdb.com/images/media/team/badge/3pxoum1598797195.png/tiny",
      "idLeague": "4334",
      "strLeague": "French Ligue 1",
      "strSeason": "2025-2026",
      "strForm": "LWLWD",
      "strDescription": "Champions League",
      "intPlayed": "28",
      "intWin": "19",
      "intLoss": "7",
      "intDraw": "2",
      "intGoalsFor": "54",
      "intGoalsAgainst": "27",
      "intGoalDifference": "27",
      "intPoints": "59",
      "dateUpdated": "2026-04-15 23:02:30"
    },
    {
      "idStanding": "9353076",
      "intRank": "3",
      "idTeam": "133711",
      "strTeam": "Lille",
      "strBadge": "https://r2.thesportsdb.com/images/media/team/badge/2giize1534005340.png/tiny",
      "idLeague": "4334",
      "strLeague": "French Ligue 1",
      "strSeason": "2025-2026",
      "strForm": "WWWWD",
      "strDescription": "Champions League",
      "intPlayed": "29",
      "intWin": "16",
      "intLoss": "8",
      "intDraw": "5",
      "intGoalsFor": "49",
      "intGoalsAgainst": "34",
      "intGoalDifference": "15",
      "intPoints": "53",
      "dateUpdated": "2026-04-15 23:02:30"
    },
    {
      "idStanding": "9353077",
      "intRank": "4",
      "idTeam": "133707",
      "strTeam": "Marseille",
      "strBadge": "https://r2.thesportsdb.com/images/media/team/badge/uutsyt1473504764.png/tiny",
      "idLeague": "4334",
      "strLeague": "French Ligue 1",
      "strSeason": "2025-2026",
      "strForm": "WLLWW",
      "strDescription": "Champions League Qualification",
      "intPlayed": "29",
      "intWin": "16",
      "intLoss": "9",
      "intDraw": "4",
      "intGoalsFor": "58",
      "intGoalsAgainst": "38",
      "intGoalDifference": "20",
      "intPoints": "52",
      "dateUpdated": "2026-04-15 23:02:30"
    },
    {
      "idStanding": "9353078",
      "intRank": "5",
      "idTeam": "133713",
      "strTeam": "Lyon",
      "strBadge": "https://r2.thesportsdb.com/images/media/team/badge/blk9771656932845.png/tiny",
      "idLeague": "4334",
      "strLeague": "French Ligue 1",
      "strSeason": "2025-2026",
      "strForm": "WDLDD",
      "strDescription": "UEFA Europa League",
      "intPlayed": "29",
      "intWin": "15",
      "intLoss": "8",
      "intDraw": "6",
      "intGoalsFor": "43",
      "intGoalsAgainst": "29",
      "intGoalDifference": "14",
      "intPoints": "51",
      "dateUpdated": "2026-04-15 23:02:30"
    }
  ]
}